trsfile/VERSION.txt
trsfile/__init__.py
trsfile/common.py
trsfile/compatibility.py
trsfile/parametermap.py
trsfile/standardparameters.py
trsfile/trace.py
trsfile/trace_set.py
trsfile/traceparameter.py
trsfile/utils.py
trsfile/converters/__init__.py
trsfile/converters/chipwhisperer.py
trsfile/engine/__init__.py
trsfile/engine/engine.py
trsfile/engine/file.py
trsfile/engine/trs.py
trsfile-2.2.3.dist-info/licenses/LICENSE
trsfile-2.2.3.dist-info/METADATA
trsfile-2.2.3.dist-info/WHEEL
trsfile-2.2.3.dist-info/top_level.txt
trsfile-2.2.3.dist-info/RECORD
