Metadata-Version: 2.4
Name: trsfile
Version: 2.2.3
Summary: Library to read and create Riscure Inspector trace set files (.trs)
Home-page: https://github.com/riscure/python-trsfile
Maintainer: Riscure
Maintainer-email: inforequest@riscure.com
License: BSD 3-Clause Clear License
Project-URL: Documentation, https://trsfile.readthedocs.io/en/latest
Project-URL: Bug Reports, https://github.com/riscure/python-trsfile/issues
Project-URL: Riscure, https://www.riscure.com
Keywords: trs,trace,inspector,riscure
Classifier: Development Status :: 4 - Beta
Classifier: Programming Language :: Python :: 3
Classifier: License :: OSI Approved :: BSD License
Classifier: Topic :: Utilities
Classifier: Operating System :: OS Independent
License-File: LICENSE
Requires-Dist: numpy<3,>=1.24
Provides-Extra: dev
Requires-Dist: sphinx; extra == "dev"
Requires-Dist: sphinx-autobuild; extra == "dev"
Requires-Dist: sphinx_rtd_theme; extra == "dev"
Requires-Dist: m2r2; extra == "dev"
Dynamic: license-file
